daspython/__init__.py
daspython/das.py
daspython/auth/__init__.py
daspython/auth/authenticate.py
daspython/client/__init__.py
daspython/common/__init__.py
daspython/common/api.py
daspython/common/response.py
daspython/dastypes/__init__.py
daspython/dastypes/entry.py
daspython/services/__init__.py
daspython/services/graphql_server.py
daspython/services/alcs/__init__.py
daspython/services/alcs/aclservice.py
daspython/services/attributes/__init__.py
daspython/services/attributes/attributeservice.py
daspython/services/digitalobjects/__init__.py
daspython/services/digitalobjects/digitalobjectservice.py
daspython/services/entries/__init__.py
daspython/services/entries/entryservice.py
daspython/services/entryfields/__init__.py
daspython/services/entryfields/entryfieldservice.py
daspython/services/searches/__init__.py
daspython/services/searches/searchservice.py
daspython-4.0.11.dist-info/licenses/LICENSE
daspython-4.0.11.dist-info/METADATA
daspython-4.0.11.dist-info/WHEEL
daspython-4.0.11.dist-info/top_level.txt
daspython-4.0.11.dist-info/RECORD
