Metadata-Version: 2.4
Name: daspython
Version: 4.0.11
Summary: DAS api client.
Author: Royal Netherlands Institute for Sea Research
Project-URL: Homepage, https://git.nioz.nl/ict-projects/das-python
Project-URL: Bug Tracker, https://git.nioz.nl/ict-projects/das-python/-/issues
Classifier: Programming Language :: Python :: 3
Classifier: License :: OSI Approved :: MIT License
Classifier: Operating System :: OS Independent
Requires-Python: >=3.11
License-File: LICENSE
Requires-Dist: requests>=2.26.0
Requires-Dist: pandas>=1.3.4
Requires-Dist: numpy>=1.21.4
Requires-Dist: pytz>=2021.3
Requires-Dist: pyyaml>=6.0
Requires-Dist: python-dateutil>=2.8.2
Requires-Dist: pydantic>=1.8.2
Requires-Dist: typing-extensions>=3.10.0.2
Dynamic: license-file
